vts-0.1.2.dist-info/METADATA
vts-0.1.2.dist-info/WHEEL
vts-0.1.2.dist-info/license_files/LICENSE-APACHE
vts-0.1.2.dist-info/license_files/LICENSE-MIT
vts/py.typed
vts/_vts/py.typed
vts/_vts/arch.pyi
vts/__init__.py
vts/arch/__init__.py
vts/_vts.abi3.so
vts-0.1.2.dist-info/RECORD
