Metadata-Version: 2.3
Name: vts
Version: 0.1.2
Classifier: Development Status :: 1 - Planning
Classifier: License :: OSI Approved :: Apache Software License
Classifier: License :: OSI Approved :: MIT License
Classifier: Programming Language :: Python
Classifier: Typing :: Typed
License-File: LICENSE-APACHE
License-File: LICENSE-MIT
Summary: A framework for SFPGA architecture exploration
Author-email: Rikus Honey <rikushoney2@gmail.com>
Requires-Python: >=3.10
Project-URL: Homepage, https://github.com/rikushoney/vts
Project-URL: Repository, https://github.com/rikushoney/vts
